AUTHORS
CHANGELOG.txt
DESCRIPTION
LICENSE
MANIFEST.in
README.rst
setup.cfg
setup.py
django_multilingual_survey.egg-info/PKG-INFO
django_multilingual_survey.egg-info/SOURCES.txt
django_multilingual_survey.egg-info/dependency_links.txt
django_multilingual_survey.egg-info/requires.txt
django_multilingual_survey.egg-info/top_level.txt
multilingual_survey/__init__.py
multilingual_survey/admin.py
multilingual_survey/forms.py
multilingual_survey/models.py
multilingual_survey/urls.py
multilingual_survey/views.py
multilingual_survey/locale/de/LC_MESSAGES/django.mo
multilingual_survey/locale/de/LC_MESSAGES/django.po
multilingual_survey/migrations/0001_initial.py
multilingual_survey/migrations/__init__.py
multilingual_survey/south_migrations/0001_initial.py
multilingual_survey/south_migrations/0002_auto__del_field_surveyquestion_position__del_field_surveyanswer_positi.py
multilingual_survey/south_migrations/0003_auto__add_field_surveytranslation_description.py
multilingual_survey/south_migrations/0004_auto__add_field_surveyresponse_session_id.py
multilingual_survey/south_migrations/__init__.py
multilingual_survey/static/.empty
multilingual_survey/static/multilingual_survey/.empty
multilingual_survey/templates/multilingual_survey/.empty
multilingual_survey/templates/multilingual_survey/survey_detail.html
multilingual_survey/templates/multilingual_survey/survey_report_admin.html
multilingual_survey/templates/multilingual_survey/survey_report_list.html
multilingual_survey/templatetags/__init__.py
multilingual_survey/templatetags/survey_tags.py
multilingual_survey/tests/__init__.py
multilingual_survey/tests/forms_tests.py
multilingual_survey/tests/models_tests.py
multilingual_survey/tests/settings.py
multilingual_survey/tests/tag_tests.py
multilingual_survey/tests/test_settings.py
multilingual_survey/tests/urls.py
multilingual_survey/tests/views_tests.py
multilingual_survey/tests/test_app/__init__.py
multilingual_survey/tests/test_app/models.py
multilingual_survey/tests/test_app/templates/400.html
multilingual_survey/tests/test_app/templates/500.html
multilingual_survey/tests/test_app/templates/base.html