Metadata-Version: 1.0
Name: django-multilingual-survey
Version: 1.0
Summary: Survey app that allows questions and answers to be created in several languages.
